{
  "name": "resilient",
  "description": "Fault tolerant and cliend-side balanced full featured HTTP client for distributed and reactive systems",
  "version": "0.3.1",
  "license": "MIT",
  "repository": "resilient-http/resilient.js",
  "author": "Tomas Aparicio",
  "main": "./resilient.js",
  "scripts": [
    "resilient.js",
    "resilient.min.js",
    "resilient.min.js.map"
  ],
  "keywords": [
    "fault",
    "tolerant",
    "balance",
    "ajax",
    "http",
    "https",
    "xhr",
    "request",
    "client",
    "agent",
    "distributed",
    "resilience",
    "reactive",
    "balancer",
    "hydra",
    "rest",
    "fallback",
    "consul"
  ]
}
